otv/__init__.py
otv/globals.py
otv/options.py
otv/ortho.py
otv/otv.py
otv/util.py
otv-1.0.1.dist-info/DESCRIPTION.rst
otv-1.0.1.dist-info/METADATA
otv-1.0.1.dist-info/RECORD
otv-1.0.1.dist-info/WHEEL
otv-1.0.1.dist-info/entry_points.txt
otv-1.0.1.dist-info/metadata.json
otv-1.0.1.dist-info/top_level.txt
