Metadata-Version: 2.0
Name: otv
Version: 1.0.1
Summary: Ortho4XP Tile Validator
Home-page: https://github.com/dyoung522/otv
Author: Donovan C. Young
Author-email: dyoung522@gmail.com
License: MIT
Keywords: ortho4xp,x-plane
Platform: UNKNOWN
Classifier: Programming Language :: Python
Classifier: Programming Language :: Python :: 3
Classifier: Development Status :: 4 - Beta
Classifier: Environment :: Console
Classifier: Intended Audience :: End Users/Desktop
Classifier: License :: OSI Approved :: MIT License
Classifier: Operating System :: OS Independent
Classifier: Topic :: Games/Entertainment
Classifier: Topic :: Games/Entertainment :: Simulation
Classifier: Topic :: Utilities
Requires-Python: >=3
Requires-Dist: colorama
Requires-Dist: tqdm
